vipaxel/__init__.py
vipaxel/constants.py
vipaxel/html_reporting.py
vipaxel/plot_wrappers.py
vipaxel/run_tardb.py
vipaxel/tar_database.py
vipaxel/template_parsing.py
vipaxel/units.py
vipaxel-0.2.5.dist-info/LICENSE
vipaxel-0.2.5.dist-info/METADATA
vipaxel-0.2.5.dist-info/WHEEL
vipaxel-0.2.5.dist-info/entry_points.txt
vipaxel-0.2.5.dist-info/RECORD
