Metadata-Version: 2.3
Name: vipaxel
Version: 0.2.5
Summary: Collection of Dataframe helpers to plot and store data
Author: Joe Shmo
Author-email: joe.burge.iii@gmail.com
Requires-Python: >=3.10
Classifier: Programming Language :: Python :: 3
Classifier: Programming Language :: Python :: 3.10
Classifier: Programming Language :: Python :: 3.11
Classifier: Programming Language :: Python :: 3.12
Classifier: Programming Language :: Python :: 3.13
Requires-Dist: pint (>=0.24.4,<0.25.0)
Requires-Dist: plotly (>=6.0.1,<7.0.0)
Requires-Dist: polars (>=1.29.0,<2.0.0)
Requires-Dist: pyyaml (>=6.0.2,<7.0.0)
